crpapi.py
opensecrets_crpapi-0.2.2.dist-info/DESCRIPTION.rst
opensecrets_crpapi-0.2.2.dist-info/METADATA
opensecrets_crpapi-0.2.2.dist-info/RECORD
opensecrets_crpapi-0.2.2.dist-info/WHEEL
opensecrets_crpapi-0.2.2.dist-info/metadata.json
opensecrets_crpapi-0.2.2.dist-info/top_level.txt
